{"files": ["Almacen 13 - Temporada 5 Completa [BluRay Rip 720p][Cap. 501_506][AC3 2.0 Castellano]/Almacen_13_5x01-Un_Mundo_Aterrador.mkv (643.5 MB)", "Almacen 13 - Temporada 5 Completa [BluRay Rip 720p][Cap. 501_506][AC3 2.0 Castellano]/Almacen_13_5x02-Servicios_Secretos.mkv (643.6 MB)", "Almacen 13 - Temporada 5 Completa [BluRay Rip 720p][Cap. 501_506][AC3 2.0 Castellano]/Almacen_13_5x03-Un_Dia_Memorable.mkv (638.4 MB)", "Almacen 13 - Temporada 5 Completa [BluRay Rip 720p][Cap. 501_506][AC3 2.0 Castellano]/Almacen_13_5x04-Seduccion_Salvaje.mkv (642.8 MB)", "Almacen 13 - Temporada 5 Completa [BluRay Rip 720p][Cap. 501_506][AC3 2.0 Castellano]/Almacen_13_5x05-Cangku_Shisi.mkv (642.9 MB)", "Almacen 13 - Temporada 5 Completa [BluRay Rip 720p][Cap. 501_506][AC3 2.0 Castellano]/Almacen_13_5x06-Sin_Fin.mkv (654.2 MB)", "Almacen 13 - Temporada 5 Completa [BluRay Rip 720p][Cap. 501_506][AC3 2.0 Castellano]/Importante leer !!!!!.txt (0.30 kB)", "Almacen 13 - Temporada 5 Completa [BluRay Rip 720p][Cap. 501_506][AC3 2.0 Castellano]/www.DIVXATOPE.com.url (877.5 kB)", "Almacen 13 - Temporada 5 Completa [BluRay Rip 720p][Cap. 501_506][AC3 2.0 Castellano]/www.newpct.com.url (0.11 kB)", "Almacen 13 - Temporada 5 Completa [BluRay Rip 720p][Cap. 501_506][AC3 2.0 Castellano]/www.newpct1.com.url (0.20 kB)"], "update_date": "2017-01-15 18:08:42", "seeders": 7, "hash": "3a4ab16621b8ee3d43b31dc55951102914195cbe", "name": "Almacen 13 - Temporada 5 Completa [BluRay Rip 720p][Cap. 501_506][AC3 2.0 Castellano]", "total_size": "3.87 GB", "leechers": 0}