{"files": ["Castle - Temporada 8 [HDTV 720p][Cap.819][AC3 5.1 Espa単ol Castellano]/Cstl720p8x19 [www.newpct1.com].mkv (1.62 GB)", "Castle - Temporada 8 [HDTV 720p][Cap.819][AC3 5.1 Espa単ol Castellano]/Importante leer !!!!!.txt (0.30 kB)", "Castle - Temporada 8 [HDTV 720p][Cap.819][AC3 5.1 Espa単ol Castellano]/www.DIVXATOPE.com.url (877.5 kB)"], "update_date": "2017-01-26 07:05:43", "seeders": 0, "hash": "d31b9b81758ebfb328898ac64259b724429c1608", "name": "Castle - Temporada 8 [HDTV 720p][Cap.819][AC3 5.1 Espa単ol Castellano]", "total_size": "1.63 GB", "leechers": 2}