{"files": ["Cronicas Vampiricas - Temporada 6 [HDTV 720p][Cap.611][AC3 5.1 Espa単ol Castellano]/CV611720p [www.newpct1.com].mkv (1.62 GB)", "Cronicas Vampiricas - Temporada 6 [HDTV 720p][Cap.611][AC3 5.1 Espa単ol Castellano]/Importante leer !!!!!.txt (0.30 kB)", "Cronicas Vampiricas - Temporada 6 [HDTV 720p][Cap.611][AC3 5.1 Espa単ol Castellano]/www.DIVXATOPE.com.url (877.5 kB)"], "update_date": "2017-01-26 07:57:39", "seeders": 3, "hash": "4866f168d41f33b1f9def7c8bba515983f361575", "name": "Cronicas Vampiricas - Temporada 6 [HDTV 720p][Cap.611][AC3 5.1 Espa単ol Castellano]", "total_size": "1.62 GB", "leechers": 0}