{"files": ["IZombie - Temporada 2 [HDTV 720p][Cap.214][AC3 5.1 Espa単ol Castellano]/Importante leer !!!!!.txt (0.30 kB)", "IZombie - Temporada 2 [HDTV 720p][Cap.214][AC3 5.1 Espa単ol Castellano]/Izom720p2x14 [www.newpct1.com].mkv (1.66 GB)", "IZombie - Temporada 2 [HDTV 720p][Cap.214][AC3 5.1 Espa単ol Castellano]/www.newpct1.com.url (877.5 kB)"], "update_date": "2017-01-19 07:38:29", "seeders": 2, "hash": "c8a7a9e524f79d3aeef8c4fd477010c63b577848", "name": "IZombie - Temporada 2 [HDTV 720p][Cap.214][AC3 5.1 Espa単ol Castellano]", "total_size": "1.66 GB", "leechers": 2}