{"files": ["Scream Queens - Temporada 1 [HDTV 720p][Cap.107][V.O. Subt. Castellano]/Importante leer !!!!!.txt (0.30 kB)", "Scream Queens - Temporada 1 [HDTV 720p][Cap.107][V.O. Subt. Castellano]/Scream Queens - Temporada 1 [HDTV 720p][Cap.107][V.O. Subt. Castellano].mkv (1.24 GB)", "Scream Queens - Temporada 1 [HDTV 720p][Cap.107][V.O. Subt. Castellano]/www.DIVXATOPE.com.url (877.5 kB)"], "update_date": "2017-01-16 08:20:49", "seeders": 0, "hash": "7503b5436ee3a3b6a6c7e40cc577e72651fafde5", "name": "Scream Queens - Temporada 1 [HDTV 720p][Cap.107][V.O. Subt. Castellano]", "total_size": "1.24 GB", "leechers": 1}