{"files": ["Helix - Temporada 1 [HDTV 720p][Cap.108][AC3 5.1 Espa単ol Castellano]/He108720p [www.newpct1.com].mkv (1.68 GB)", "Helix - Temporada 1 [HDTV 720p][Cap.108][AC3 5.1 Espa単ol Castellano]/Importante leer !!!!!.txt (0.30 kB)", "Helix - Temporada 1 [HDTV 720p][Cap.108][AC3 5.1 Espa単ol Castellano]/www.DIVXATOPE.com.url (877.5 kB)"], "update_date": "2017-01-19 07:34:25", "seeders": 0, "hash": "9a55dbb179956e3a2839fd74b8a80008d6752252", "name": "Helix - Temporada 1 [HDTV 720p][Cap.108][AC3 5.1 Espa単ol Castellano]", "total_size": "1.68 GB", "leechers": 2}