{"files": ["Primeval New World - Temporada 1 [HDTV 720p][Cap.109][AC3 5.1 Eslpa単ol Castellano]/Importante leer !!!!!.txt (0.30 kB)", "Primeval New World - Temporada 1 [HDTV 720p][Cap.109][AC3 5.1 Eslpa単ol Castellano]/Primeval720p1x09 [www.newpct1.com].mkv (1.51 GB)", "Primeval New World - Temporada 1 [HDTV 720p][Cap.109][AC3 5.1 Eslpa単ol Castellano]/TUmejorTorrent.url (0.12 kB)"], "update_date": "2017-01-16 06:56:16", "seeders": 11, "hash": "45291fc307eaf72215b7e04e05c6a9b3584defd5", "name": "Primeval New World - Temporada 1 [HDTV 720p][Cap.109][AC3 5.1 Eslpa単ol Castellano]", "total_size": "1.51 GB", "leechers": 0}