{"files": ["Arrow - Temporada 3 [HDTV][Cap.304][V.O.Sub. Espa単ol Castellano]/Arro303vos [www.newpct1.com].avi (483.9 MB)", "Arrow - Temporada 3 [HDTV][Cap.304][V.O.Sub. Espa単ol Castellano]/Importante leer !!!!!.txt (0.30 kB)", "Arrow - Temporada 3 [HDTV][Cap.304][V.O.Sub. Espa単ol Castellano]/www.DIVXATOPE.com.url (877.5 kB)"], "update_date": "2017-01-16 07:28:22", "seeders": 0, "hash": "31e7f1e17e5b23d4fa44c273b90194f9a86b2c19", "name": "Arrow - Temporada 3 [HDTV][Cap.304][V.O.Sub. Espa単ol Castellano]", "total_size": "484.8 MB", "leechers": 0}