{"files": ["Vikingos - Temporada 4 [HDTV 720p][Cap.409][AC3 5.1 Español Castellano]/AYUDA.txt (0.26 kB)", "Vikingos - Temporada 4 [HDTV 720p][Cap.409][AC3 5.1 Español Castellano]/CONTRASEÑA PARA DESCOMPRIMIR.txt (0.57 kB)", "Vikingos - Temporada 4 [HDTV 720p][Cap.409][AC3 5.1 Español Castellano]/TuMejortorrent.com.url (0.26 kB)", "Vikingos - Temporada 4 [HDTV 720p][Cap.409][AC3 5.1 Español Castellano]/Vikingos 720p 4x09 [www.tumejortorrent.com].rar (1.76 GB)"], "update_date": "2017-01-18 19:59:47", "seeders": 97, "hash": "847b6739752dd5a4d49972736d04b192924bb846", "name": "Vikingos - Temporada 4 [HDTV 720p][Cap.409][AC3 5.1 Español Castellano]", "total_size": "1.76 GB", "leechers": 25}