{"files": ["Arrow - Temporada 1 [HDTV 720px][Cap.122][AC3 5.1 Espa単ol Castellano]/Arrow720p122 [www.newpct.com].mkv (1.71 GB)", "Arrow - Temporada 1 [HDTV 720px][Cap.122][AC3 5.1 Espa単ol Castellano]/Importante Leer !!.txt (0.31 kB)", "Arrow - Temporada 1 [HDTV 720px][Cap.122][AC3 5.1 Espa単ol Castellano]/www.NEWPCT.com.url (877.5 kB)"], "update_date": "2017-01-25 22:18:32", "seeders": 5, "hash": "d926afb9e6d75c35ae2b14c5a649c5fb21268ea1", "name": "Arrow - Temporada 1 [HDTV 720px][Cap.122][AC3 5.1 Espa単ol Castellano]", "total_size": "1.71 GB", "leechers": 2}