{"files": ["The Flash - Temporada 1 [HDTV][Cap.105][V.O.Sub. Espa単ol Castellano]/Importante leer !!!!!.txt (0.30 kB)", "The Flash - Temporada 1 [HDTV][Cap.105][V.O.Sub. Espa単ol Castellano]/TF105vos [www.newpct1.com].avi (484.7 MB)", "The Flash - Temporada 1 [HDTV][Cap.105][V.O.Sub. Espa単ol Castellano]/www.DIVXATOPE.com.url (877.5 kB)"], "update_date": "2017-01-16 07:16:16", "seeders": 0, "hash": "a327500e1efc00d27476fe9224f6710f2eadc2b8", "name": "The Flash - Temporada 1 [HDTV][Cap.105][V.O.Sub. Espa単ol Castellano]", "total_size": "485.6 MB", "leechers": 0}