{"files": ["The Librarians - Temporada 2 [HDTV][Cap.209][Espa単ol Castellano]/Importante leer !!!!!.txt (0.30 kB)", "The Librarians - Temporada 2 [HDTV][Cap.209][Espa単ol Castellano]/TL209 [www.newpct1.com].avi (654.3 MB)", "The Librarians - Temporada 2 [HDTV][Cap.209][Espa単ol Castellano]/www.DIVXATOPE.com.url (877.5 kB)"], "update_date": "2017-01-18 19:52:09", "seeders": 5, "hash": "7386a45e75f1e807cf9c0dcf6aede3333035d6dc", "name": "The Librarians - Temporada 2 [HDTV][Cap.209][Espa単ol Castellano]", "total_size": "655.2 MB", "leechers": 0}