{"files": ["Vikingos Al Descubierto - Temporada 4 [HDTV][Cap.421][Español Castellano]/Importante leer !!!!!.txt (0.30 kB)", "Vikingos Al Descubierto - Temporada 4 [HDTV][Cap.421][Español Castellano]/TUmejorTorrent.url (0.12 kB)", "Vikingos Al Descubierto - Temporada 4 [HDTV][Cap.421][Español Castellano]/VikingosAlDescubierto_421_WWW.NEWPCT1.COM.avi (515.6 MB)", "Vikingos Al Descubierto - Temporada 4 [HDTV][Cap.421][Español Castellano]/www.DIVXATOPE1.com.url (877.5 kB)", "Vikingos Al Descubierto - Temporada 4 [HDTV][Cap.421][Español Castellano]/www.newpct.com.url (0.11 kB)", "Vikingos Al Descubierto - Temporada 4 [HDTV][Cap.421][Español Castellano]/www.newpct1.com.url (0.20 kB)"], "update_date": "2017-01-15 17:29:42", "seeders": 111, "hash": "c46793adfef4945daaa098b1dea0821d829bcb6a", "name": "Vikingos Al Descubierto - Temporada 4 [HDTV][Cap.421][Español Castellano]", "total_size": "516.4 MB", "leechers": 40}