{"files": ["Stag - Temporada 1 [HDTV 720p][Cap.102][AC3 5.1 Español Castellano]/Importante leer !!!!!.txt (0.30 kB)", "Stag - Temporada 1 [HDTV 720p][Cap.102][AC3 5.1 Español Castellano]/Stag720p_102_WWW.NEWPCT1.COM.mkv (2.03 GB)", "Stag - Temporada 1 [HDTV 720p][Cap.102][AC3 5.1 Español Castellano]/www.DIVXATOPE.com.url (877.5 kB)", "Stag - Temporada 1 [HDTV 720p][Cap.102][AC3 5.1 Español Castellano]/www.newpct.com.url (0.11 kB)", "Stag - Temporada 1 [HDTV 720p][Cap.102][AC3 5.1 Español Castellano]/www.newpct1.com.url (0.20 kB)"], "update_date": "2017-01-15 17:18:34", "seeders": 5, "hash": "6f02ee6527d55c09fcb148544f919173b19d3b10", "name": "Stag - Temporada 1 [HDTV 720p][Cap.102][AC3 5.1 Español Castellano]", "total_size": "2.03 GB", "leechers": 1}