{"files": ["Scream - Temporada 2 [HDTV 720p][Cap.208][AC3 5.1 Espa単ol Castellano]/Importante leer !!!!!.txt (0.30 kB)", "Scream - Temporada 2 [HDTV 720p][Cap.208][AC3 5.1 Espa単ol Castellano]/Scream 720p 2x08 [www.newpct1.com].mkv (1.51 GB)", "Scream - Temporada 2 [HDTV 720p][Cap.208][AC3 5.1 Espa単ol Castellano]/www.newpct1.com.url (877.5 kB)"], "update_date": "2017-01-15 19:58:22", "seeders": 5, "hash": "f9adc7222c0e6ac74cb04bb093ceeb26a7e2ff17", "name": "Scream - Temporada 2 [HDTV 720p][Cap.208][AC3 5.1 Espa単ol Castellano]", "total_size": "1.51 GB", "leechers": 1}