{"files": ["Ascension - Temporada 1 [HDTV 720p][Cap.102][AC3 5.1 Espa単ol Castellano]/Asc102720p [www.newpct1.com].mkv (1.65 GB)", "Ascension - Temporada 1 [HDTV 720p][Cap.102][AC3 5.1 Espa単ol Castellano]/Importante leer !!!!!.txt (0.30 kB)", "Ascension - Temporada 1 [HDTV 720p][Cap.102][AC3 5.1 Espa単ol Castellano]/www.DIVXATOPE.com.url (877.5 kB)"], "update_date": "2017-01-16 08:42:50", "seeders": 0, "hash": "57490c1ccf6e4b11d2361c29cd61754e7a2151bf", "name": "Ascension - Temporada 1 [HDTV 720p][Cap.102][AC3 5.1 Espa単ol Castellano]", "total_size": "1.65 GB", "leechers": 0}