{"files": ["Pequeñas Mentirosas - Temporada 6 [HDTV 720p][Cap.620][AC3 5.1 Español Castellano]/Importante leer !!!!!.txt (0.30 kB)", "Pequeñas Mentirosas - Temporada 6 [HDTV 720p][Cap.620][AC3 5.1 Español Castellano]/Pequeñas Mentirosas 720p 6x20 [www.newpct1.com].mkv (1.61 GB)", "Pequeñas Mentirosas - Temporada 6 [HDTV 720p][Cap.620][AC3 5.1 Español Castellano]/www.TUmejortorrent.com.com.url (877.5 kB)"], "update_date": "2017-01-15 18:09:59", "seeders": 5, "hash": "4dee771e14c3004fc6c53a038265d8291f5e0f9c", "name": "Pequeñas Mentirosas - Temporada 6 [HDTV 720p][Cap.620][AC3 5.1 Español Castellano]", "total_size": "1.61 GB", "leechers": 3}