{"files": ["The Man in the High Castle - Temporada 1 [HDTV 720p][Cap.108_109][AC3 5.1 Español Castellano]/Importante leer !!!!!.txt (0.30 kB)", "The Man in the High Castle - Temporada 1 [HDTV 720p][Cap.108_109][AC3 5.1 Español Castellano]/TMITHCastle720p1x08 [www.newpct1.com].mkv (1.68 GB)", "The Man in the High Castle - Temporada 1 [HDTV 720p][Cap.108_109][AC3 5.1 Español Castellano]/TMITHCastle720p1x09 [www.newpct1.com].mkv (1.49 GB)", "The Man in the High Castle - Temporada 1 [HDTV 720p][Cap.108_109][AC3 5.1 Español Castellano]/www.newpct1.com.url (877.5 kB)"], "update_date": "2017-01-18 20:00:21", "seeders": 46, "hash": "79ad02c71f863e1ac4030269adb5326c263525ab", "name": "The Man in the High Castle - Temporada 1 [HDTV 720p][Cap.108_109][AC3 5.1 Español Castellano]", "total_size": "3.17 GB", "leechers": 6}