{"files": ["Jericho - Temporada 1 Completa [BluRay Rip 720p][Cap. 101_122][AC3 2.0 Español Castellano]/Importante leer !!!!!.txt (0.30 kB)", "Jericho - Temporada 1 Completa [BluRay Rip 720p][Cap. 101_122][AC3 2.0 Español Castellano]/Jericho_01x01_Las_17_Primeras_Horas.mkv (1.31 GB)", "Jericho - Temporada 1 Completa [BluRay Rip 720p][Cap. 101_122][AC3 2.0 Español Castellano]/Jericho_01x02_Lluvia_Radiactiva.mkv (1.34 GB)", "Jericho - Temporada 1 Completa [BluRay Rip 720p][Cap. 101_122][AC3 2.0 Español Castellano]/Jericho_01x03_Los_Cuatro_Jinetes.mkv (1.46 GB)", "Jericho - Temporada 1 Completa [BluRay Rip 720p][Cap. 101_122][AC3 2.0 Español Castellano]/Jericho_01x04_Los_Muros_De_Jericho.mkv (1.29 GB)", "Jericho - Temporada 1 Completa [BluRay Rip 720p][Cap. 101_122][AC3 2.0 Español Castellano]/Jericho_01x05_Respuesta_Federal.mkv (1.40 GB)", "Jericho - Temporada 1 Completa [BluRay Rip 720p][Cap. 101_122][AC3 2.0 Español Castellano]/Jericho_01x06_9-02.mkv (1.33 GB)", "Jericho - Temporada 1 Completa [BluRay Rip 720p][Cap. 101_122][AC3 2.0 Español Castellano]/Jericho_01x07_Larga_Vida_Al_Alcalde.mkv (1.44 GB)", "Jericho - Temporada 1 Completa [BluRay Rip 720p][Cap. 101_122][AC3 2.0 Español Castellano]/Jericho_01x08_Rouge_River.mkv (1.35 GB)", "Jericho - Temporada 1 Completa [BluRay Rip 720p][Cap. 101_122][AC3 2.0 Español Castellano]/Jericho_01x09_Cruce_De_Caminos.mkv (1.39 GB)", "Jericho - Temporada 1 Completa [BluRay Rip 720p][Cap. 101_122][AC3 2.0 Español Castellano]/Jericho_01x10_Amenaza_Roja.mkv (1.33 GB)", "Jericho - Temporada 1 Completa [BluRay Rip 720p][Cap. 101_122][AC3 2.0 Español Castellano]/Jericho_01x11_Vox_Populi.mkv (1.49 GB)", "Jericho - Temporada 1 Completa [BluRay Rip 720p][Cap. 101_122][AC3 2.0 Español Castellano]/Jericho_01x12_El_Dia_Antes.mkv (1.37 GB)", "Jericho - Temporada 1 Completa [BluRay Rip 720p][Cap. 101_122][AC3 2.0 Español Castellano]/Jericho_01x13_Black_Jack.mkv (1.36 GB)", "Jericho - Temporada 1 Completa [BluRay Rip 720p][Cap. 101_122][AC3 2.0 Español Castellano]/Jericho_01x14_Corazon_De_Invierno.mkv (1.50 GB)", "Jericho - Temporada 1 Completa [BluRay Rip 720p][Cap. 101_122][AC3 2.0 Español Castellano]/Jericho_01x15_Semper_Fidelis.mkv (1.35 GB)", "Jericho - Temporada 1 Completa [BluRay Rip 720p][Cap. 101_122][AC3 2.0 Español Castellano]/Jericho_01x16_El_Fin_Del_Invierno.mkv (1.50 GB)", "Jericho - Temporada 1 Completa [BluRay Rip 720p][Cap. 101_122][AC3 2.0 Español Castellano]/Jericho_01x17_El_Terrorista.mkv (1.38 GB)", "Jericho - Temporada 1 Completa [BluRay Rip 720p][Cap. 101_122][AC3 2.0 Español Castellano]/Jericho_01x18_A_K_A_.mkv (1.37 GB)", "Jericho - Temporada 1 Completa [BluRay Rip 720p][Cap. 101_122][AC3 2.0 Español Castellano]/Jericho_01x19_Casus_Belli.mkv (1.43 GB)", "Jericho - Temporada 1 Completa [BluRay Rip 720p][Cap. 101_122][AC3 2.0 Español Castellano]/Jericho_01x20_Uno_Si_Es_Por_Tierra.mkv (1.38 GB)", "Jericho - Temporada 1 Completa [BluRay Rip 720p][Cap. 101_122][AC3 2.0 Español Castellano]/Jericho_01x21_Suma_De_Voluntades.mkv (1.43 GB)", "Jericho - Temporada 1 Completa [BluRay Rip 720p][Cap. 101_122][AC3 2.0 Español Castellano]/Jericho_01x22_Por_Que_Luchamos.mkv (1.44 GB)", "Jericho - Temporada 1 Completa [BluRay Rip 720p][Cap. 101_122][AC3 2.0 Español Castellano]/www.DIVXATOPE.com.url (877.5 kB)"], "update_date": "2017-01-18 19:48:09", "seeders": 2, "hash": "5cac31b82fe0b07c853ad3849e4ddbf40cab17a8", "name": "Jericho - Temporada 1 Completa [BluRay Rip 720p][Cap. 101_122][AC3 2.0 Español Castellano]", "total_size": "30.64 GB", "leechers": 2}