{"files": ["Criminal Minds - Temporada 11 [HDTV 720p][Cap.1114][V.O. Subt. Castellano]/Criminal Minds - Temporada 11 [HDTV 720p][Cap.1114][V.O. Subt. Castellano].mkv (1.06 GB)", "Criminal Minds - Temporada 11 [HDTV 720p][Cap.1114][V.O. Subt. Castellano]/Importante leer !!!!!.txt (0.30 kB)", "Criminal Minds - Temporada 11 [HDTV 720p][Cap.1114][V.O. Subt. Castellano]/www.DIVXATOPE.com.url (877.5 kB)"], "update_date": "2017-01-15 19:25:26", "seeders": 0, "hash": "057ba57476bd909a88cb74cf02419ab6b4dc71db", "name": "Criminal Minds - Temporada 11 [HDTV 720p][Cap.1114][V.O. Subt. Castellano]", "total_size": "1.06 GB", "leechers": 0}