{"files": ["Black-ish - Temporada 1 [HDTV][Cap.123][Espa単ol Castellano]/Bkish123 [www.newpct1.com].avi (255.6 MB)", "Black-ish - Temporada 1 [HDTV][Cap.123][Espa単ol Castellano]/Importante leer !!!!!.txt (0.30 kB)", "Black-ish - Temporada 1 [HDTV][Cap.123][Espa単ol Castellano]/www.DIVXATOPE.com.url (877.5 kB)"], "update_date": "2017-01-16 07:05:32", "seeders": 3, "hash": "44219a5473aa9a7fb4379f9c4aef16600323349c", "name": "Black-ish - Temporada 1 [HDTV][Cap.123][Espa単ol Castellano]", "total_size": "256.5 MB", "leechers": 0}