{"update_date": "2017-01-24 07:28:54", "title": "Gravity_Falls", "url": "http://www.newpct1.com/series-hd/gravity_falls/2867", "image": "http://www.newpct1.com/pictures/c/2867_gravity_falls.jpg", "capitulos": 1, "id": -1127492894, "capitulos_list": [{"title": "Gravity Falls - Temporada 1 Completa  [BDremux 720p][Cap.101_120][AC3 2.0 Castellano]", "url": "http://www.newpct1.com/serie/gravity-falls/capitulo-101-al-20/", "torrent_link": "http://tumejorjuego.com/descargar/index.php?link=descargar-torrent/1479627186_gravity-falls---temporada-1-completa--bluray-720p/", "date": "20-11-2016", "id": 504645442, "unit": "GB", "size": 3.9}]}