{"update_date": "2017-02-27 20:34:17", "title": "Weeds", "url": "http://www.newpct1.com/series-hd/weeds/2324", "image": "http://www.newpct1.com/pictures/c/2324_weeds.jpg", "capitulos": 8, "id": -1394403489, "capitulos_list": [{"title": "Weeds - Temporada 1 Completa  [BluRay Rip 720p][Cap. 101_110][AC3 2.0 Español Castellano]", "url": "http://www.newpct1.com/serie/weeds/capitulo-101-al-10/", "torrent_link": "http://tumejorjuego.com/descargar/index.php?link=descargar-torrent/1448098041_weeds---temporada-1-completa--bluray-720p/", "date": "21-11-2015", "id": 1726013796, "unit": "GB", "size": 9.8}, {"title": "Weeds - Temporada 3 Completa  [BluRay Rip 720p][Cap. 301_315][MP3 2.0 Español Castellano]", "url": "http://www.newpct1.com/serie/weeds/capitulo-301-al-15/", "torrent_link": "http://tumejorjuego.com/descargar/index.php?link=descargar-torrent/1448264803_weeds---temporada-3-completa--bluray-720p/", "date": "23-11-2015", "id": -511176047, "unit": "GB", "size": 14.6}, {"title": "Weeds - Temporada 4 Completa  [BluRay Rip 720p][Cap. 401_413][AC3 2.0 Español Castellano]", "url": "http://www.newpct1.com/serie/weeds/capitulo-401-al-13/", "torrent_link": "http://tumejorjuego.com/descargar/index.php?link=descargar-torrent/1448359598_weeds---temporada-4-completa--bluray-720p/", "date": "24-11-2015", "id": -1140428694, "unit": "GB", "size": 12.7}, {"title": "Weeds - Temporada 2 Completa  [BluRay Rip 720p][Cap. 201_212][AC3 2.0 Español Castellano]", "url": "http://www.newpct1.com/serie/weeds/capitulo-201-al-12/", "torrent_link": "http://tumejorjuego.com/descargar/index.php?link=descargar-torrent/1448187103_weeds---temporada-2-completa--bluray-720p/", "date": "22-11-2015", "id": 33335115, "unit": "GB", "size": 1.2}, {"title": "Weeds - Temporada 6 Completa  [BluRay Rip 720p][Cap. 601_613][AC3 5.1 Español Castellano]", "url": "http://www.newpct1.com/serie/weeds/capitulo-601-al-13/", "torrent_link": "http://tumejorjuego.com/descargar/index.php?link=descargar-torrent/1448529431_weeds---temporada-6-completa--hdtv-720p-ac3-51/", "date": "26-11-2015", "id": 248856656, "unit": "GB", "size": 12.7}, {"title": "Weeds - Temporada 5 Completa  [BluRay Rip 720p][Cap. 501_513][MP3 2.0 Español Castellano]", "url": "http://www.newpct1.com/serie/weeds/capitulo-501-al-13/", "torrent_link": "http://tumejorjuego.com/descargar/index.php?link=descargar-torrent/1448443297_weeds---temporada-5-completa--bluray-720p/", "date": "25-11-2015", "id": -156205711, "unit": "GB", "size": 1.3}, {"title": "Weeds - Temporada 7 Completa  [BluRay Rip 720p][Cap. 701_713][AC3 5.1 Español Castellano]", "url": "http://www.newpct1.com/serie/weeds/capitulo-701-al-13/", "torrent_link": "http://tumejorjuego.com/descargar/index.php?link=descargar-torrent/1448628330_weeds---temporada-7-completa--hdtv-720p-ac3-51/", "date": "27-11-2015", "id": -536570761, "unit": "GB", "size": 12.7}, {"title": "Weeds - Temporada 8 Completa  [BluRay Rip 720p][Cap. 801_813][AC3 2.0 Español Castellano]", "url": "http://www.newpct1.com/serie/weeds/capitulo-801-al-13/", "torrent_link": "http://tumejorjuego.com/descargar/index.php?link=descargar-torrent/1448705053_weeds---temporada-8-completa--bluray-720p/", "date": "28-11-2015", "id": -1417113954, "unit": "GB", "size": 12.7}]}