{"update_date": "2017-01-24 08:49:36", "title": "The Affair", "url": "http://www.newpct1.com/series-hd/the-affair/1919", "image": "http://www.newpct1.com/pictures/c/1919_the-affair-.jpg", "capitulos": 29, "id": -1477512890, "capitulos_list": [{"title": "The Affair - Temporada 1  [HDTV 720p][Cap.105][AC3 5.1 Español Castellano]", "url": "http://www.newpct1.com/serie/the-affair-/capitulo-105/", "torrent_link": "http://tumejorjuego.com/download/index.php?link=descargar-torrent/062320_the-affair-temporada-1-hdtv-720p-ac3-51.html", "date": "05-01-2015", "id": -1141454076, "unit": "GB", "size": 1.9}, {"title": "The Affair - Temporada 1  [HDTV 720p][Cap.101][AC3 5.1 Español Castellano]", "url": "http://www.newpct1.com/serie/the-affair-/capitulo-101/", "torrent_link": "http://tumejorjuego.com/download/index.php?link=descargar-torrent/062254_the-affair-temporada-1-hdtv-720p-ac3-51.html", "date": "03-01-2015", "id": -1145454072, "unit": "GB", "size": 1.9}, {"title": "The Affair - Temporada 1  [HDTV 720p][Cap.107][AC3 5.1 Español Castellano]", "url": "http://www.newpct1.com/serie/the-affair-/capitulo-107/", "torrent_link": "http://tumejorjuego.com/download/index.php?link=descargar-torrent/062508_the-affair-temporada-1-hdtv-720p-ac3-51.html", "date": "11-01-2015", "id": -1143454066, "unit": "GB", "size": 2.2}, {"title": "The Affair - Temporada 3  [HDTV 720p][Cap.304][AC3 5.1 Español Castellano]", "url": "http://www.newpct1.com/descargar-seriehd/the-affair/capitulo-34/hdtv-720p-ac3-5-1/", "torrent_link": "http://tumejorjuego.com/descargar/index.php?link=descargar-torrent/90100_the-affair-temporada-3-hdtv-720p-cap-304-ac3-5-1-espaa-ol-castellano/", "date": "22-12-2016", "id": -1471297904, "unit": "GB", "size": 2.0}, {"title": "The Affair - Temporada 2  [HDTV 720p][Cap.208][AC3 5.1 Español Castellano]", "url": "http://www.newpct1.com/serie/the-affair-/capitulo-208/", "torrent_link": "http://tumejorjuego.com/descargar/index.php?link=descargar-torrent/1449097422_the-affair---temporada-2--hdtv-720p-ac3-51/", "date": "03-12-2015", "id": -1722350318, "unit": "GB", "size": 2.0}, {"title": "The Affair - Temporada 2  [HDTV 720p][Cap.211][AC3 5.1 Español Castellano]", "url": "http://www.newpct1.com/serie/the-affair-/capitulo-211/", "torrent_link": "http://tumejorjuego.com/descargar/index.php?link=descargar-torrent/1450907603_the-affair---temporada-2--hdtv-720p-ac3-51/", "date": "23-12-2015", "id": -975970284, "unit": "GB", "size": 2.1}, {"title": "The Affair - Temporada 1  [HDTV 720p][Cap.108][AC3 5.1 Español Castellano]", "url": "http://www.newpct1.com/serie/the-affair-/capitulo-108/", "torrent_link": "http://tumejorjuego.com/download/index.php?link=descargar-torrent/062512_the-affair-temporada-1-hdtv-720p-ac3-51.html", "date": "11-01-2015", "id": -1154454097, "unit": "GB", "size": 1.9}, {"title": "The Affair - Temporada 2  [HDTV 720p][Cap.206][AC3 5.1 Español Castellano]", "url": "http://www.newpct1.com/serie/the-affair-/capitulo-206/", "torrent_link": "http://tumejorjuego.com/descargar/index.php?link=descargar-torrent/1447888579_the-affair---temporada-2--hdtv-720p-ac3-51/", "date": "19-11-2015", "id": -1724350308, "unit": "GB", "size": 2.0}, {"title": "The Affair - Temporada 3  [HDTV 720p][Cap.301][AC3 5.1 Español Castellano]", "url": "http://www.newpct1.com/serie/the-affair-/capitulo-301/", "torrent_link": "http://tumejorjuego.com/descargar/index.php?link=descargar-torrent/1480580828_the-affair---temporada-3--hdtv-720p-ac3-51/", "date": "01-12-2016", "id": 2013720738, "unit": "GB", "size": 2.0}, {"title": "The Affair - Temporada 2  [HDTV 720p][Cap.205][AC3 5.1 Español Castellano]", "url": "http://www.newpct1.com/serie/the-affair-/capitulo-205/", "torrent_link": "http://tumejorjuego.com/descargar/index.php?link=descargar-torrent/1447280054_the-affair---temporada-2--hdtv-720p-ac3-51/", "date": "11-11-2015", "id": -1727350363, "unit": "GB", "size": 1.8}, {"title": "The Affair - Temporada 2  [HDTV 720p][Cap.201][AC3 5.1 Español Castellano]", "url": "http://www.newpct1.com/serie/the-affair-/capitulo-201/", "torrent_link": "http://tumejorjuego.com/descargar/index.php?link=descargar-torrent/1444892567_the-affair---temporada-2--hdtv-720p-ac3-51/", "date": "15-10-2015", "id": -1731350359, "unit": "GB", "size": 1.8}, {"title": "The Affair - Temporada 3  [HDTV 720p][Cap.306][AC3 5.1 Español Castellano]", "url": "http://www.newpct1.com/descargar-seriehd/the-affair/capitulo-36/hdtv-720p-ac3-5-1/", "torrent_link": "http://tumejorjuego.com/descargar/index.php?link=descargar-torrent/90684_the-affair-temporada-3-hdtv-720p-cap-306-ac3-5-1-espaa-ol-castellano/", "date": "12-01-2017", "id": 1921611946, "unit": "GB", "size": 2.0}, {"title": "The Affair - Temporada 2  [HDTV 720p][Cap.203][AC3 5.1 Español Castellano]", "url": "http://www.newpct1.com/serie/the-affair-/capitulo-203/", "torrent_link": "http://tumejorjuego.com/descargar/index.php?link=descargar-torrent/1446072331_the-affair---temporada-2--hdtv-720p-ac3-51/", "date": "28-10-2015", "id": -1729350353, "unit": "GB", "size": 1.6}, {"title": "The Affair - Temporada 3  [HDTV 720p][Cap.307][AC3 5.1 Español Castellano]", "url": "http://www.newpct1.com/descargar-seriehd/the-affair/capitulo-37/hdtv-720p-ac3-5-1/", "torrent_link": "http://tumejorjuego.com/descargar/index.php?link=descargar-torrent/90905_the-affair-temporada-3-hdtv-720p-cap-307-ac3-5-1-espaa-ol-castellano/", "date": "19-01-2017", "id": 1405595457, "unit": "GB", "size": 2.0}, {"title": "The Affair - Temporada 1  [HDTV 720p][Cap.104][AC3 5.1 Español Castellano]", "url": "http://www.newpct1.com/serie/the-affair-/capitulo-104/", "torrent_link": "http://tumejorjuego.com/download/index.php?link=descargar-torrent/062286_the-affair-temporada-1-hdtv-720p-ac3-51.html", "date": "04-01-2015", "id": -1142454077, "unit": "GB", "size": 1.9}, {"title": "The Affair - Temporada 1  [HDTV 720p][Cap.109][AC3 5.1 Español Castellano]", "url": "http://www.newpct1.com/serie/the-affair-/capitulo-109/", "torrent_link": "http://tumejorjuego.com/download/index.php?link=descargar-torrent/062537_the-affair-temporada-1-hdtv-720p-ac3-51.html", "date": "12-01-2015", "id": -1153454112, "unit": "GB", "size": 2.3}, {"title": "The Affair - Temporada 1  [HDTV 720p][Cap.106][AC3 5.1 Español Castellano]", "url": "http://www.newpct1.com/serie/the-affair-/capitulo-106/", "torrent_link": "http://tumejorjuego.com/download/index.php?link=descargar-torrent/062341_the-affair-temporada-1-hdtv-720p-ac3-51.html", "date": "06-01-2015", "id": -1144454067, "unit": "GB", "size": 1.9}, {"title": "The Affair - Temporada 1  [HDTV 720p][Cap.110][AC3 5.1 Español Castellano]", "url": "http://www.newpct1.com/serie/the-affair-/capitulo-110/", "torrent_link": "http://tumejorjuego.com/download/index.php?link=descargar-torrent/062541_the-affair-temporada-1-hdtv-720p-ac3-51.html", "date": "12-01-2015", "id": -1867834034, "unit": "GB", "size": 1.9}, {"title": "The Affair - Temporada 2  [HDTV 720p][Cap.209][AC3 5.1 Español Castellano]", "url": "http://www.newpct1.com/serie/the-affair-/capitulo-209/", "torrent_link": "http://tumejorjuego.com/descargar/index.php?link=descargar-torrent/1449701471_the-affair---temporada-2--hdtv-720p-ac3-51/", "date": "09-12-2015", "id": -1723350319, "unit": "GB", "size": 2.0}, {"title": "The Affair - Temporada 2  [HDTV 720p][Cap.210][AC3 5.1 Español Castellano]", "url": "http://www.newpct1.com/serie/the-affair-/capitulo-210/", "torrent_link": "http://tumejorjuego.com/descargar/index.php?link=descargar-torrent/1450305772_the-affair---temporada-2--hdtv-720p-ac3-51/", "date": "16-12-2015", "id": -976970285, "unit": "GB", "size": 2.0}, {"title": "The Affair - Temporada 3  [HDTV 720p][Cap.302][AC3 5.1 Español Castellano]", "url": "http://www.newpct1.com/descargar-seriehd/the-affair/capitulo-32/hdtv-720p-ac3-5-1/", "torrent_link": "http://tumejorjuego.com/descargar/index.php?link=descargar-torrent/89495_the-affair-temporada-3-hdtv-720p-cap-302-ac3-5-1-espaa-ol-castellano/", "date": "08-12-2016", "id": -1935077802, "unit": "GB", "size": 1.9}, {"title": "The Affair - Temporada 3  [HDTV 720p][Cap.305][AC3 5.1 Español Castellano]", "url": "http://www.newpct1.com/descargar-seriehd/the-affair/capitulo-35/hdtv-720p-ac3-5-1/", "torrent_link": "http://tumejorjuego.com/descargar/index.php?link=descargar-torrent/90305_the-affair-temporada-3-hdtv-720p-cap-305-ac3-5-1-espaa-ol-castellano/", "date": "29-12-2016", "id": -1841423913, "unit": "GB", "size": 2.0}, {"title": "The Affair (Proper) - Temporada 2  [HDTV 720p][Cap.207][AC3 5.1 Español Castellano]", "url": "http://www.newpct1.com/serie/the-affair-/capitulo-207/", "torrent_link": "http://tumejorjuego.com/descargar/index.php?link=descargar-torrent/1448619150_the-affair--proper----temporada-2--hdtv-720p-ac3-51/", "date": "27-11-2015", "id": -1725350309, "unit": "GB", "size": 2.3}, {"title": "The Affair - Temporada 2  [HDTV 720p][Cap.212][AC3 5.1 Español Castellano]", "url": "http://www.newpct1.com/serie/the-affair-/capitulo-212/", "torrent_link": "http://tumejorjuego.com/descargar/index.php?link=descargar-torrent/1451513703_the-affair---temporada-2--hdtv-720p-ac3-51/", "date": "30-12-2015", "id": -978970275, "unit": "GB", "size": 2.3}, {"title": "The Affair - Temporada 2  [HDTV 720p][Cap.202][AC3 5.1 Español Castellano]", "url": "http://www.newpct1.com/serie/the-affair-/capitulo-202/", "torrent_link": "http://tumejorjuego.com/descargar/index.php?link=descargar-torrent/1445515043_the-affair---temporada-2--hdtv-720p-ac3-51/", "date": "22-10-2015", "id": -1728350368, "unit": "GB", "size": 1.6}, {"title": "The Affair - Temporada 2  [HDTV 720p][Cap.204][AC3 5.1 Español Castellano]", "url": "http://www.newpct1.com/serie/the-affair-/capitulo-204/", "torrent_link": "http://tumejorjuego.com/descargar/index.php?link=descargar-torrent/1446710015_the-affair---temporada-2--hdtv-720p-ac3-51/", "date": "05-11-2015", "id": -1726350362, "unit": "GB", "size": 1.6}, {"title": "The Affair - Temporada 1  [HDTV 720p][Cap.102][AC3 5.1 Español Castellano]", "url": "http://www.newpct1.com/serie/the-affair-/capitulo-102/", "torrent_link": "http://tumejorjuego.com/download/index.php?link=descargar-torrent/062268_the-affair-temporada-1-hdtv-720p-ac3-51.html", "date": "04-01-2015", "id": -1148454063, "unit": "GB", "size": 1.9}, {"title": "The Affair - Temporada 1  [HDTV 720p][Cap.103][AC3 5.1 Español Castellano]", "url": "http://www.newpct1.com/serie/the-affair-/capitulo-103/", "torrent_link": "http://tumejorjuego.com/download/index.php?link=descargar-torrent/062269_the-affair-temporada-1-hdtv-720p-ac3-51.html", "date": "04-01-2015", "id": -1147454062, "unit": "GB", "size": 1.9}, {"title": "The Affair - Temporada 3  [HDTV 720p][Cap.303][AC3 5.1 Español Castellano]", "url": "http://www.newpct1.com/descargar-seriehd/the-affair/capitulo-33/hdtv-720p-ac3-5-1/", "torrent_link": "http://tumejorjuego.com/descargar/index.php?link=descargar-torrent/89812_the-affair-temporada-3-hdtv-720p-cap-303-ac3-5-1-espaa-ol-castellano/", "date": "15-12-2016", "id": 912969341, "unit": "GB", "size": 1.8}]}