{"update_date": "2017-02-06 21:04:41", "title": "Riverdale", "url": "http://www.newpct1.com/series/riverdale/3065", "image": "http://www.newpct1.com/pictures/c/3065_riverdale.jpg", "capitulos": 1, "id": -397321854, "capitulos_list": [{"title": "Riverdale - Temporada 1  [HDTV][Cap.101][Español Castellano]", "url": "http://www.newpct1.com/descargar-serie/riverdale/capitulo-11/hdtv/", "torrent_link": "http://tumejorjuego.com/descargar/index.php?link=descargar-torrent/91467_riverdale-temporada-1-hdtv-cap-101-espaa-ol-castellano/", "date": "04-02-2017", "id": 2099075050, "unit": "MB", "size": 500.0}]}