{"update_date": "2017-01-24 08:37:41", "title": "Bitten", "url": "http://www.newpct1.com/series/bitten/3029", "image": "http://www.newpct1.com/pictures/c/3029_bitten.jpg", "capitulos": 4, "id": -859312435, "capitulos_list": [{"title": "Bitten - Temporada 1  [HDTV][Cap.104_109][Espa単ol Castellano]", "url": "http://www.newpct1.com/descargar-serie/bitten/capitulo-14/hdtv/", "torrent_link": "http://tumejorjuego.com/descargar/index.php?link=descargar-torrent/90999_bitten-temporada-1-hdtv-cap-104-109-espaa-ol-castellano/", "date": "21-01-2017", "id": -1878771504, "unit": "GB", "size": 3.9}, {"title": "Bitten - Temporada 1  [HDTV][Cap.101][Espa単ol Castellano]", "url": "http://www.newpct1.com/descargar-serie/bitten/capitulo-11/hdtv/", "torrent_link": "http://tumejorjuego.com/descargar/index.php?link=descargar-torrent/90699_bitten-temporada-1-hdtv-cap-101-espaa-ol-castellano/", "date": "12-01-2017", "id": -1692536775, "unit": "MB", "size": 500.0}, {"title": "Bitten - Temporada 1  [HDTV][Cap.110_113][Espa単ol Castellano]", "url": "http://www.newpct1.com/descargar-serie/bitten/capitulo-110/hdtv/", "torrent_link": "http://tumejorjuego.com/descargar/index.php?link=descargar-torrent/91022_bitten-temporada-1-hdtv-cap-110-113-espaa-ol-castellano/", "date": "22-01-2017", "id": 1727212922, "unit": "GB", "size": 1.9}, {"title": "Bitten - Temporada 1  [HDTV][Cap.102_103][Espa単ol Castellano]", "url": "http://www.newpct1.com/descargar-serie/bitten/capitulo-12/hdtv/", "torrent_link": "http://tumejorjuego.com/descargar/index.php?link=descargar-torrent/90774_bitten-temporada-1-hdtv-cap-102-103-espaa-ol-castellano/", "date": "14-01-2017", "id": -675591942, "unit": "MB", "size": 1000.0}]}